quantum_lab/__init__.py
quantum_lab/jobs.py
quantum_lab/resources.py
quantum_lab-0.2.0.dist-info/METADATA
quantum_lab-0.2.0.dist-info/WHEEL
quantum_lab-0.2.0.dist-info/top_level.txt
quantum_lab-0.2.0.dist-info/RECORD
